hyperopt/__init__.py
hyperopt/algobase.py
hyperopt/anneal.py
hyperopt/atpe.py
hyperopt/base.py
hyperopt/criteria.py
hyperopt/early_stop.py
hyperopt/exceptions.py
hyperopt/fmin.py
hyperopt/graph_viz.py
hyperopt/hp.py
hyperopt/ipy.py
hyperopt/main.py
hyperopt/mix.py
hyperopt/mongoexp.py
hyperopt/plotting.py
hyperopt/progress.py
hyperopt/pyll_utils.py
hyperopt/rand.py
hyperopt/rdists.py
hyperopt/spark.py
hyperopt/std_out_err_redirect_tqdm.py
hyperopt/tpe.py
hyperopt/utils.py
hyperopt/vectorize.py
hyperopt/atpe_models/model-gamma-configuration.json
hyperopt/atpe_models/model-gamma.txt
hyperopt/atpe_models/model-nEICandidates-configuration.json
hyperopt/atpe_models/model-nEICandidates.txt
hyperopt/atpe_models/model-resultFilteringAgeMultiplier-configuration.json
hyperopt/atpe_models/model-resultFilteringAgeMultiplier.txt
hyperopt/atpe_models/model-resultFilteringLossRankMultiplier-configuration.json
hyperopt/atpe_models/model-resultFilteringLossRankMultiplier.txt
hyperopt/atpe_models/model-resultFilteringMode-configuration.json
hyperopt/atpe_models/model-resultFilteringMode.txt
hyperopt/atpe_models/model-resultFilteringRandomProbability-configuration.json
hyperopt/atpe_models/model-resultFilteringRandomProbability.txt
hyperopt/atpe_models/model-secondaryCorrelationExponent-configuration.json
hyperopt/atpe_models/model-secondaryCorrelationExponent.txt
hyperopt/atpe_models/model-secondaryCorrelationMultiplier-configuration.json
hyperopt/atpe_models/model-secondaryCorrelationMultiplier.txt
hyperopt/atpe_models/model-secondaryCutoff-configuration.json
hyperopt/atpe_models/model-secondaryCutoff.txt
hyperopt/atpe_models/model-secondaryFixedProbability-configuration.json
hyperopt/atpe_models/model-secondaryFixedProbability.txt
hyperopt/atpe_models/model-secondaryLockingMode-configuration.json
hyperopt/atpe_models/model-secondaryLockingMode.txt
hyperopt/atpe_models/model-secondaryProbabilityMode-configuration.json
hyperopt/atpe_models/model-secondaryProbabilityMode.txt
hyperopt-0.2.6.dist-info/LICENSE.txt
hyperopt-0.2.6.dist-info/METADATA
hyperopt-0.2.6.dist-info/WHEEL
hyperopt-0.2.6.dist-info/entry_points.txt
hyperopt-0.2.6.dist-info/top_level.txt
hyperopt-0.2.6.dist-info/RECORD
